aws_cdk/__init__.py
aws_cdk/cli.py
aws_cdk/installer.py
aws_cdk/post_install.py
aws_cdk/runtime.py
aws_cdk/version.py
aws_cdk/__pycache__/__init__.cpython-313.pyc
aws_cdk/__pycache__/version.cpython-313.pyc
aws_cdk/node_binaries/darwin/arm64/LICENSE
aws_cdk/node_modules/aws-cdk/LICENSE
aws_cdk/node_modules/aws-cdk/NOTICE
aws_cdk/node_modules/aws-cdk/README.md
aws_cdk/node_modules/aws-cdk/THIRD_PARTY_LICENSES
aws_cdk/node_modules/aws-cdk/build-info.json
aws_cdk/node_modules/aws-cdk/db.json.gz
aws_cdk/node_modules/aws-cdk/metadata.json
aws_cdk/node_modules/aws-cdk/package.json
aws_cdk/node_modules/aws-cdk/release.txt
aws_cdk/node_modules/aws-cdk/bin/cdk
aws_cdk/node_modules/aws-cdk/bin/cdk.js
aws_cdk/node_modules/aws-cdk/lib/diff.d.ts
aws_cdk/node_modules/aws-cdk/lib/diff.js
aws_cdk/node_modules/aws-cdk/lib/index.d.ts
aws_cdk/node_modules/aws-cdk/lib/index.js
aws_cdk/node_modules/aws-cdk/lib/index_bg.wasm
aws_cdk/node_modules/aws-cdk/lib/init-hooks.d.ts
aws_cdk/node_modules/aws-cdk/lib/init-hooks.js
aws_cdk/node_modules/aws-cdk/lib/init.d.ts
aws_cdk/node_modules/aws-cdk/lib/init.js
aws_cdk/node_modules/aws-cdk/lib/legacy-exports-source.d.ts
aws_cdk/node_modules/aws-cdk/lib/legacy-exports-source.js
aws_cdk/node_modules/aws-cdk/lib/legacy-exports.d.ts
aws_cdk/node_modules/aws-cdk/lib/legacy-exports.js
aws_cdk/node_modules/aws-cdk/lib/legacy-logging-source.d.ts
aws_cdk/node_modules/aws-cdk/lib/legacy-logging-source.js
aws_cdk/node_modules/aws-cdk/lib/list-stacks.d.ts
aws_cdk/node_modules/aws-cdk/lib/list-stacks.js
aws_cdk/node_modules/aws-cdk/lib/logging.d.ts
aws_cdk/node_modules/aws-cdk/lib/logging.js
aws_cdk/node_modules/aws-cdk/lib/notices.d.ts
aws_cdk/node_modules/aws-cdk/lib/notices.js
aws_cdk/node_modules/aws-cdk/lib/os.d.ts
aws_cdk/node_modules/aws-cdk/lib/os.js
aws_cdk/node_modules/aws-cdk/lib/tree.d.ts
aws_cdk/node_modules/aws-cdk/lib/tree.js
aws_cdk/node_modules/aws-cdk/lib/util.d.ts
aws_cdk/node_modules/aws-cdk/lib/util.js
aws_cdk_wrapper-2.1003.0.dev1.dist-info/LICENSE
aws_cdk_wrapper-2.1003.0.dev1.dist-info/METADATA
aws_cdk_wrapper-2.1003.0.dev1.dist-info/WHEEL
aws_cdk_wrapper-2.1003.0.dev1.dist-info/entry_points.txt
aws_cdk_wrapper-2.1003.0.dev1.dist-info/top_level.txt
aws_cdk_wrapper-2.1003.0.dev1.dist-info/RECORD
